noopy/__init__.py
noopy/__main__.py
noopy/arr.py
noopy/hook.py
noopy/lst.py
noopy/str.py
noopy/math/__init__.py
noopy/util/__init__.py
noopy/util/globals.py
noopy/util/namedhook.py
noopy-0.11.0.dist-info/licenses/LICENSE
noopy-0.11.0.dist-info/licenses/LICENSE.GPLv3
noopy-0.11.0.dist-info/licenses/LICENSE.RPTv1
noopy-0.11.0.dist-info/METADATA
noopy-0.11.0.dist-info/WHEEL
noopy-0.11.0.dist-info/top_level.txt
noopy-0.11.0.dist-info/zip-safe
noopy-0.11.0.dist-info/RECORD
